[
  {
    "_id": "2022-08-24T17:27:34Z",
    "author": "Jimmy Dane",
    "title": "Biden Pledges Nearly $3 Billion To Ukraine In Largest U.S. Military Aid Package Yet",
    "image": "https://example.com/biden-ukraine-aid.jpg",
    "date": "Wednesday, August 24, 2022",
    "category": "Politics",
    "details": "In a landmark move, U.S. President Joe Biden announced nearly $3 billion in military aid to Ukraine, marking the largest such package since the conflict with Russia began in February 2022. The aid package, which includes advanced missile defense systems, artillery ammunition, drones, and armored vehicles, is part of Washington’s continued commitment to support Kyiv in its efforts to defend its sovereignty. According to U.S. officials, the weapons and resources provided will significantly bolster Ukraine’s defensive and offensive capabilities over the coming months. This assistance also includes long-term contracts for the production of weaponry, signaling that the United States anticipates the war could extend into the foreseeable future. Biden emphasized that the aid package is not only a direct response to Ukraine’s immediate needs but also part of a strategic effort to strengthen Ukraine’s long-term security infrastructure. The announcement coincided with Ukraine’s Independence Day, a symbolic gesture aimed at reinforcing solidarity between the two nations. The aid has been met with praise from Kyiv, where Ukrainian President Volodymyr Zelenskyy expressed deep gratitude, stating that such assistance could prove decisive on the battlefield. However, the move has drawn mixed reactions domestically within the United States, with some lawmakers questioning the long-term financial implications of sustained aid. Critics argue that the U.S. should focus more on its domestic issues, while proponents maintain that defending Ukraine is essential for preserving international order and deterring future acts of aggression by authoritarian states. Internationally, the announcement has been welcomed by NATO allies, many of whom have also stepped up their military support for Ukraine in recent months. Russia, on the other hand, has condemned the package as an escalation, warning of severe consequences. Despite these threats, the Biden administration remains steadfast, underscoring that the cost of inaction would be far greater in the long run. Analysts note that this aid package could mark a turning point in the war, potentially enabling Ukraine to reclaim lost territory and stabilize its defense lines.",
    "excerpt": "U.S. President Joe Biden has ...",
    "rating": 4.5,
    "views": 41
  },
  {
    "_id": "2023-02-14T10:15:00Z",
    "author": "Sarah Lee",
    "title": "Tech Giants Announce Breakthrough In Quantum Computing",
    "image": "https://example.com/quantum-computing.jpg",
    "date": "Tuesday, February 14, 2023",
    "category": "Technology",
    "details": "In a landmark move, U.S. President Joe Biden announced nearly $3 billion in military aid to Ukraine, marking the largest such package since the conflict with Russia began in February 2022. The aid package, which includes advanced missile defense systems, artillery ammunition, drones, and armored vehicles, is part of Washington’s continued commitment to support Kyiv in its efforts to defend its sovereignty. According to U.S. officials, the weapons and resources provided will significantly bolster Ukraine’s defensive and offensive capabilities over the coming months. This assistance also includes long-term contracts for the production of weaponry, signaling that the United States anticipates the war could extend into the foreseeable future. Biden emphasized that the aid package is not only a direct response to Ukraine’s immediate needs but also part of a strategic effort to strengthen Ukraine’s long-term security infrastructure. The announcement coincided with Ukraine’s Independence Day, a symbolic gesture aimed at reinforcing solidarity between the two nations. The aid has been met with praise from Kyiv, where Ukrainian President Volodymyr Zelenskyy expressed deep gratitude, stating that such assistance could prove decisive on the battlefield. However, the move has drawn mixed reactions domestically within the United States, with some lawmakers questioning the long-term financial implications of sustained aid. Critics argue that the U.S. should focus more on its domestic issues, while proponents maintain that defending Ukraine is essential for preserving international order and deterring future acts of aggression by authoritarian states. Internationally, the announcement has been welcomed by NATO allies, many of whom have also stepped up their military support for Ukraine in recent months. Russia, on the other hand, has condemned the package as an escalation, warning of severe consequences. Despite these threats, the Biden administration remains steadfast, underscoring that the cost of inaction would be far greater in the long run. Analysts note that this aid package could mark a turning point in the war, potentially enabling Ukraine to reclaim lost territory and stabilize its defense lines.",

    "excerpt": "Major tech companies have unveiled a major breakthrough in quantum computing...",
    "rating": 4.8,
    "views": 152
  },
  {
    "_id": "2023-06-10T08:45:00Z",
    "author": "Michael Carter",
    "title": "Local Farmers Embrace Organic Farming Methods",
    "image": "https://example.com/organic-farming.jpg",
    "date": "Saturday, June 10, 2023",
    "category": "Environment",
    "details": "In a landmark move, U.S. President Joe Biden announced nearly $3 billion in military aid to Ukraine, marking the largest such package since the conflict with Russia began in February 2022. The aid package, which includes advanced missile defense systems, artillery ammunition, drones, and armored vehicles, is part of Washington’s continued commitment to support Kyiv in its efforts to defend its sovereignty. According to U.S. officials, the weapons and resources provided will significantly bolster Ukraine’s defensive and offensive capabilities over the coming months. This assistance also includes long-term contracts for the production of weaponry, signaling that the United States anticipates the war could extend into the foreseeable future. Biden emphasized that the aid package is not only a direct response to Ukraine’s immediate needs but also part of a strategic effort to strengthen Ukraine’s long-term security infrastructure. The announcement coincided with Ukraine’s Independence Day, a symbolic gesture aimed at reinforcing solidarity between the two nations. The aid has been met with praise from Kyiv, where Ukrainian President Volodymyr Zelenskyy expressed deep gratitude, stating that such assistance could prove decisive on the battlefield. However, the move has drawn mixed reactions domestically within the United States, with some lawmakers questioning the long-term financial implications of sustained aid. Critics argue that the U.S. should focus more on its domestic issues, while proponents maintain that defending Ukraine is essential for preserving international order and deterring future acts of aggression by authoritarian states. Internationally, the announcement has been welcomed by NATO allies, many of whom have also stepped up their military support for Ukraine in recent months. Russia, on the other hand, has condemned the package as an escalation, warning of severe consequences. Despite these threats, the Biden administration remains steadfast, underscoring that the cost of inaction would be far greater in the long run. Analysts note that this aid package could mark a turning point in the war, potentially enabling Ukraine to reclaim lost territory and stabilize its defense lines.",

    "excerpt": "Farmers across the region are shifting to organic farming techniques...",
    "rating": 4.2,
    "views": 89
  },
  {
    "_id": "2023-06-10T08:45:02Z",
    "author": "Michael Carter",
    "title": "Local Farmers Embrace Organic Farming Methods",
    "image": "https://example.com/organic-farming.jpg",
    "date": "Saturday, June 10, 2023",
    "category": "Environment",
    "details": "In a landmark move, U.S. President Joe Biden announced nearly $3 billion in military aid to Ukraine, marking the largest such package since the conflict with Russia began in February 2022. The aid package, which includes advanced missile defense systems, artillery ammunition, drones, and armored vehicles, is part of Washington’s continued commitment to support Kyiv in its efforts to defend its sovereignty. According to U.S. officials, the weapons and resources provided will significantly bolster Ukraine’s defensive and offensive capabilities over the coming months. This assistance also includes long-term contracts for the production of weaponry, signaling that the United States anticipates the war could extend into the foreseeable future. Biden emphasized that the aid package is not only a direct response to Ukraine’s immediate needs but also part of a strategic effort to strengthen Ukraine’s long-term security infrastructure. The announcement coincided with Ukraine’s Independence Day, a symbolic gesture aimed at reinforcing solidarity between the two nations. The aid has been met with praise from Kyiv, where Ukrainian President Volodymyr Zelenskyy expressed deep gratitude, stating that such assistance could prove decisive on the battlefield. However, the move has drawn mixed reactions domestically within the United States, with some lawmakers questioning the long-term financial implications of sustained aid. Critics argue that the U.S. should focus more on its domestic issues, while proponents maintain that defending Ukraine is essential for preserving international order and deterring future acts of aggression by authoritarian states. Internationally, the announcement has been welcomed by NATO allies, many of whom have also stepped up their military support for Ukraine in recent months. Russia, on the other hand, has condemned the package as an escalation, warning of severe consequences. Despite these threats, the Biden administration remains steadfast, underscoring that the cost of inaction would be far greater in the long run. Analysts note that this aid package could mark a turning point in the war, potentially enabling Ukraine to reclaim lost territory and stabilize its defense lines.",

    "excerpt": "Farmers across the region are shifting to organic farming techniques...",
    "rating": 4.2,
    "views": 89
  },
  {
    "_id": "2023-09-21T14:30:00Z",
    "author": "Emily Johnson",
    "title": "Record-Breaking Performance at World Athletics Championships",
    "image": "https://example.com/athletics-championship.jpg",
    "date": "Thursday, September 21, 2023",
    "category": "Sports",
    "details": "In a landmark move, U.S. President Joe Biden announced nearly $3 billion in military aid to Ukraine, marking the largest such package since the conflict with Russia began in February 2022. The aid package, which includes advanced missile defense systems, artillery ammunition, drones, and armored vehicles, is part of Washington’s continued commitment to support Kyiv in its efforts to defend its sovereignty. According to U.S. officials, the weapons and resources provided will significantly bolster Ukraine’s defensive and offensive capabilities over the coming months. This assistance also includes long-term contracts for the production of weaponry, signaling that the United States anticipates the war could extend into the foreseeable future. Biden emphasized that the aid package is not only a direct response to Ukraine’s immediate needs but also part of a strategic effort to strengthen Ukraine’s long-term security infrastructure. The announcement coincided with Ukraine’s Independence Day, a symbolic gesture aimed at reinforcing solidarity between the two nations. The aid has been met with praise from Kyiv, where Ukrainian President Volodymyr Zelenskyy expressed deep gratitude, stating that such assistance could prove decisive on the battlefield. However, the move has drawn mixed reactions domestically within the United States, with some lawmakers questioning the long-term financial implications of sustained aid. Critics argue that the U.S. should focus more on its domestic issues, while proponents maintain that defending Ukraine is essential for preserving international order and deterring future acts of aggression by authoritarian states. Internationally, the announcement has been welcomed by NATO allies, many of whom have also stepped up their military support for Ukraine in recent months. Russia, on the other hand, has condemned the package as an escalation, warning of severe consequences. Despite these threats, the Biden administration remains steadfast, underscoring that the cost of inaction would be far greater in the long run. Analysts note that this aid package could mark a turning point in the war, potentially enabling Ukraine to reclaim lost territory and stabilize its defense lines.",
    "excerpt": "Athletes set multiple world records at this year’s World Athletics Championships...",
    "rating": 4.6,
    "views": 201
  },
  {
    "_id": "2023-12-05T19:20:00Z",
    "author": "David Kim",
    "title": "New Art Exhibition Opens in Downtown Gallery",
    "image": "https://example.com/art-exhibition.jpg",
    "date": "Tuesday, December 5, 2023",
    "category": "Art & Culture",
    "details": "In a landmark move, U.S. President Joe Biden announced nearly $3 billion in military aid to Ukraine, marking the largest such package since the conflict with Russia began in February 2022. The aid package, which includes advanced missile defense systems, artillery ammunition, drones, and armored vehicles, is part of Washington’s continued commitment to support Kyiv in its efforts to defend its sovereignty. According to U.S. officials, the weapons and resources provided will significantly bolster Ukraine’s defensive and offensive capabilities over the coming months. This assistance also includes long-term contracts for the production of weaponry, signaling that the United States anticipates the war could extend into the foreseeable future. Biden emphasized that the aid package is not only a direct response to Ukraine’s immediate needs but also part of a strategic effort to strengthen Ukraine’s long-term security infrastructure. The announcement coincided with Ukraine’s Independence Day, a symbolic gesture aimed at reinforcing solidarity between the two nations. The aid has been met with praise from Kyiv, where Ukrainian President Volodymyr Zelenskyy expressed deep gratitude, stating that such assistance could prove decisive on the battlefield. However, the move has drawn mixed reactions domestically within the United States, with some lawmakers questioning the long-term financial implications of sustained aid. Critics argue that the U.S. should focus more on its domestic issues, while proponents maintain that defending Ukraine is essential for preserving international order and deterring future acts of aggression by authoritarian states. Internationally, the announcement has been welcomed by NATO allies, many of whom have also stepped up their military support for Ukraine in recent months. Russia, on the other hand, has condemned the package as an escalation, warning of severe consequences. Despite these threats, the Biden administration remains steadfast, underscoring that the cost of inaction would be far greater in the long run. Analysts note that this aid package could mark a turning point in the war, potentially enabling Ukraine to reclaim lost territory and stabilize its defense lines.",

    "excerpt": "The downtown gallery is showcasing an exciting new collection from emerging artists...",
    "rating": 4.9,
    "views": 64
  }
]
